django_remote_model/provider/provider_fields_generator.py
django_remote_model/provider/provider_serializer.py
django_remote_model/provider/provider_view_set.py
django_remote_model/remote_model/__init__.py
django_remote_model/remote_model/get_model.py
django_remote_model/remote_model/queryset.py
django_remote_model-0.1.7.dist-info/METADATA
django_remote_model-0.1.7.dist-info/WHEEL
django_remote_model-0.1.7.dist-info/top_level.txt
django_remote_model-0.1.7.dist-info/RECORD
